[
    {
        "Line":  "都営三田線",
        "Name":  "目黒",
        "Lat":  35.633272,
        "Lng":  139.7155
    },
    {
        "Line":  "都営三田線",
        "Name":  "白金台",
        "Lat":  35.637917,
        "Lng":  139.726133
    },
    {
        "Line":  "都営三田線",
        "Name":  "白金高輪",
        "Lat":  35.642903,
        "Lng":  139.734104
    },
    {
        "Line":  "都営三田線",
        "Name":  "三田",
        "Lat":  35.64818,
        "Lng":  139.748775
    },
    {
        "Line":  "都営三田線",
        "Name":  "芝公園",
        "Lat":  35.654074,
        "Lng":  139.749824
    },
    {
        "Line":  "都営三田線",
        "Name":  "御成門",
        "Lat":  35.661215,
        "Lng":  139.751535
    },
    {
        "Line":  "都営三田線",
        "Name":  "内幸町",
        "Lat":  35.66975,
        "Lng":  139.75561
    },
    {
        "Line":  "都営三田線",
        "Name":  "日比谷",
        "Lat":  35.676036,
        "Lng":  139.759998
    },
    {
        "Line":  "都営三田線",
        "Name":  "大手町",
        "Lat":  35.684856,
        "Lng":  139.762959
    },
    {
        "Line":  "都営三田線",
        "Name":  "神保町",
        "Lat":  35.695492,
        "Lng":  139.75812
    },
    {
        "Line":  "都営三田線",
        "Name":  "水道橋",
        "Lat":  35.703398,
        "Lng":  139.75516
    },
    {
        "Line":  "都営三田線",
        "Name":  "春日",
        "Lat":  35.709598,
        "Lng":  139.75325
    },
    {
        "Line":  "都営三田線",
        "Name":  "白山",
        "Lat":  35.721408,
        "Lng":  139.752136
    },
    {
        "Line":  "都営三田線",
        "Name":  "千石",
        "Lat":  35.727957,
        "Lng":  139.744792
    },
    {
        "Line":  "都営三田線",
        "Name":  "巣鴨",
        "Lat":  35.733502,
        "Lng":  139.738519
    },
    {
        "Line":  "都営三田線",
        "Name":  "西巣鴨",
        "Lat":  35.743508,
        "Lng":  139.728712
    },
    {
        "Line":  "都営三田線",
        "Name":  "新板橋",
        "Lat":  35.748785,
        "Lng":  139.720101
    },
    {
        "Line":  "都営三田線",
        "Name":  "板橋区役所前",
        "Lat":  35.751284,
        "Lng":  139.710102
    },
    {
        "Line":  "都営三田線",
        "Name":  "板橋本町",
        "Lat":  35.761339,
        "Lng":  139.705535
    },
    {
        "Line":  "都営三田線",
        "Name":  "本蓮沼",
        "Lat":  35.768782,
        "Lng":  139.702324
    },
    {
        "Line":  "都営三田線",
        "Name":  "志村坂上",
        "Lat":  35.775725,
        "Lng":  139.69538
    },
    {
        "Line":  "都営三田線",
        "Name":  "志村三丁目",
        "Lat":  35.777391,
        "Lng":  139.685937
    },
    {
        "Line":  "都営三田線",
        "Name":  "蓮根",
        "Lat":  35.784335,
        "Lng":  139.678993
    },
    {
        "Line":  "都営三田線",
        "Name":  "西台",
        "Lat":  35.78699,
        "Lng":  139.673971
    },
    {
        "Line":  "都営三田線",
        "Name":  "高島平",
        "Lat":  35.789056,
        "Lng":  139.661216
    },
    {
        "Line":  "都営三田線",
        "Name":  "新高島平",
        "Lat":  35.790189,
        "Lng":  139.654275
    },
    {
        "Line":  "都営三田線",
        "Name":  "西高島平",
        "Lat":  35.791833,
        "Lng":  139.64594
    },
    {
        "Line":  "都営新宿線",
        "Name":  "新宿",
        "Lat":  35.68869,
        "Lng":  139.698812
    },
    {
        "Line":  "都営新宿線",
        "Name":  "新宿三丁目",
        "Lat":  35.690616,
        "Lng":  139.706271
    },
    {
        "Line":  "都営新宿線",
        "Name":  "曙橋",
        "Lat":  35.692402,
        "Lng":  139.722881
    },
    {
        "Line":  "都営新宿線",
        "Name":  "市ヶ谷",
        "Lat":  35.692594,
        "Lng":  139.735794
    },
    {
        "Line":  "都営新宿線",
        "Name":  "九段下",
        "Lat":  35.695589,
        "Lng":  139.751948
    },
    {
        "Line":  "都営新宿線",
        "Name":  "神保町",
        "Lat":  35.695966,
        "Lng":  139.757606
    },
    {
        "Line":  "都営新宿線",
        "Name":  "小川町",
        "Lat":  35.695487,
        "Lng":  139.767551
    },
    {
        "Line":  "都営新宿線",
        "Name":  "岩本町",
        "Lat":  35.695534,
        "Lng":  139.775866
    },
    {
        "Line":  "都営新宿線",
        "Name":  "馬喰横山",
        "Lat":  35.69212,
        "Lng":  139.782768
    },
    {
        "Line":  "都営新宿線",
        "Name":  "浜町",
        "Lat":  35.688516,
        "Lng":  139.788154
    },
    {
        "Line":  "都営新宿線",
        "Name":  "森下",
        "Lat":  35.68796,
        "Lng":  139.797042
    },
    {
        "Line":  "都営新宿線",
        "Name":  "菊川",
        "Lat":  35.688379,
        "Lng":  139.806016
    },
    {
        "Line":  "都営新宿線",
        "Name":  "住吉",
        "Lat":  35.689073,
        "Lng":  139.815681
    },
    {
        "Line":  "都営新宿線",
        "Name":  "西大島",
        "Lat":  35.689349,
        "Lng":  139.826206
    },
    {
        "Line":  "都営新宿線",
        "Name":  "大島",
        "Lat":  35.689905,
        "Lng":  139.83565
    },
    {
        "Line":  "都営新宿線",
        "Name":  "東大島",
        "Lat":  35.690355,
        "Lng":  139.845963
    },
    {
        "Line":  "都営新宿線",
        "Name":  "船堀",
        "Lat":  35.683795,
        "Lng":  139.864258
    },
    {
        "Line":  "都営新宿線",
        "Name":  "一之江",
        "Lat":  35.686055,
        "Lng":  139.882934
    },
    {
        "Line":  "都営新宿線",
        "Name":  "瑞江",
        "Lat":  35.693318,
        "Lng":  139.89761
    },
    {
        "Line":  "都営新宿線",
        "Name":  "篠崎",
        "Lat":  35.706017,
        "Lng":  139.903698
    },
    {
        "Line":  "都営新宿線",
        "Name":  "本八幡",
        "Lat":  35.722929,
        "Lng":  139.926628
    },
    {
        "Line":  "都営大江戸線",
        "Name":  "新宿西口",
        "Lat":  35.693315,
        "Lng":  139.699155
    },
    {
        "Line":  "都営大江戸線",
        "Name":  "東新宿",
        "Lat":  35.69792,
        "Lng":  139.707549
    },
    {
        "Line":  "都営大江戸線",
        "Name":  "若松河田",
        "Lat":  35.699218,
        "Lng":  139.718184
    },
    {
        "Line":  "都営大江戸線",
        "Name":  "牛込柳町",
        "Lat":  35.699518,
        "Lng":  139.725027
    },
    {
        "Line":  "都営大江戸線",
        "Name":  "牛込神楽坂",
        "Lat":  35.700851,
        "Lng":  139.735802
    },
    {
        "Line":  "都営大江戸線",
        "Name":  "飯田橋",
        "Lat":  35.702927,
        "Lng":  139.744999
    },
    {
        "Line":  "都営大江戸線",
        "Name":  "春日",
        "Lat":  35.709598,
        "Lng":  139.75325
    },
    {
        "Line":  "都営大江戸線",
        "Name":  "本郷三丁目",
        "Lat":  35.707462,
        "Lng":  139.760095
    },
    {
        "Line":  "都営大江戸線",
        "Name":  "上野御徒町",
        "Lat":  35.707893,
        "Lng":  139.774332
    },
    {
        "Line":  "都営大江戸線",
        "Name":  "新御徒町",
        "Lat":  35.707045,
        "Lng":  139.781958
    },
    {
        "Line":  "都営大江戸線",
        "Name":  "蔵前",
        "Lat":  35.703236,
        "Lng":  139.790931
    },
    {
        "Line":  "都営大江戸線",
        "Name":  "両国",
        "Lat":  35.696881,
        "Lng":  139.797421
    },
    {
        "Line":  "都営大江戸線",
        "Name":  "森下",
        "Lat":  35.68796,
        "Lng":  139.797042
    },
    {
        "Line":  "都営大江戸線",
        "Name":  "清澄白河",
        "Lat":  35.682105,
        "Lng":  139.798851
    },
    {
        "Line":  "都営大江戸線",
        "Name":  "門前仲町",
        "Lat":  35.671851,
        "Lng":  139.796209
    },
    {
        "Line":  "都営大江戸線",
        "Name":  "月島",
        "Lat":  35.664871,
        "Lng":  139.784233
    },
    {
        "Line":  "都営大江戸線",
        "Name":  "勝どき",
        "Lat":  35.658507,
        "Lng":  139.776442
    },
    {
        "Line":  "都営大江戸線",
        "Name":  "築地市場",
        "Lat":  35.664895,
        "Lng":  139.766915
    },
    {
        "Line":  "都営大江戸線",
        "Name":  "汐留",
        "Lat":  35.663703,
        "Lng":  139.760642
    },
    {
        "Line":  "都営大江戸線",
        "Name":  "大門",
        "Lat":  35.656785,
        "Lng":  139.75466
    },
    {
        "Line":  "都営大江戸線",
        "Name":  "赤羽橋",
        "Lat":  35.655007,
        "Lng":  139.743642
    },
    {
        "Line":  "都営大江戸線",
        "Name":  "麻布十番",
        "Lat":  35.656503,
        "Lng":  139.736116
    },
    {
        "Line":  "都営大江戸線",
        "Name":  "六本木",
        "Lat":  35.663921,
        "Lng":  139.731567
    },
    {
        "Line":  "都営大江戸線",
        "Name":  "青山一丁目",
        "Lat":  35.672929,
        "Lng":  139.72396
    },
    {
        "Line":  "都営大江戸線",
        "Name":  "国立競技場",
        "Lat":  35.679831,
        "Lng":  139.714932
    },
    {
        "Line":  "都営大江戸線",
        "Name":  "代々木",
        "Lat":  35.683218,
        "Lng":  139.701666
    },
    {
        "Line":  "都営大江戸線",
        "Name":  "新宿",
        "Lat":  35.68869,
        "Lng":  139.698812
    },
    {
        "Line":  "都営大江戸線",
        "Name":  "都庁前",
        "Lat":  35.690551,
        "Lng":  139.69257
    },
    {
        "Line":  "都営大江戸線",
        "Name":  "西新宿五丁目",
        "Lat":  35.689798,
        "Lng":  139.684304
    },
    {
        "Line":  "都営大江戸線",
        "Name":  "中野坂上",
        "Lat":  35.69709,
        "Lng":  139.682279
    },
    {
        "Line":  "都営大江戸線",
        "Name":  "東中野",
        "Lat":  35.706891,
        "Lng":  139.682987
    },
    {
        "Line":  "都営大江戸線",
        "Name":  "中井",
        "Lat":  35.714035,
        "Lng":  139.686356
    },
    {
        "Line":  "都営大江戸線",
        "Name":  "落合南長崎",
        "Lat":  35.723608,
        "Lng":  139.683303
    },
    {
        "Line":  "都営大江戸線",
        "Name":  "新江古田",
        "Lat":  35.732538,
        "Lng":  139.670653
    },
    {
        "Line":  "都営大江戸線",
        "Name":  "練馬",
        "Lat":  35.737404,
        "Lng":  139.65477
    },
    {
        "Line":  "都営大江戸線",
        "Name":  "豊島園",
        "Lat":  35.742067,
        "Lng":  139.64911
    },
    {
        "Line":  "都営大江戸線",
        "Name":  "練馬春日町",
        "Lat":  35.751452,
        "Lng":  139.640236
    },
    {
        "Line":  "都営大江戸線",
        "Name":  "光が丘",
        "Lat":  35.758526,
        "Lng":  139.628603
    }
]
